distinctid/__init__.py
distinctid-1.0.4.dist-info/LICENSE.txt
distinctid-1.0.4.dist-info/METADATA
distinctid-1.0.4.dist-info/WHEEL
distinctid-1.0.4.dist-info/top_level.txt
distinctid-1.0.4.dist-info/RECORD
