Metadata-Version: 2.1
Name: distinctid
Version: 1.0.4
Summary: A unique number generator
Author-email: Chukwudi Nwachukwu <chukwudi.nwachukwu@pitchcardinal.com>
Project-URL: Homepage, https://github.com/ichux/distinctid
Project-URL: Issues, https://github.com/ichux/distinctid/issues
Classifier: Programming Language :: Python :: 3
Classifier: License :: OSI Approved :: MIT License
Classifier: Operating System :: POSIX :: Linux
Requires-Python: >=3.10
License-File: LICENSE.txt
